{
  "scanned_at": "2026-07-17T15:06:35.781503",
  "mode": "range",
  "total_scanned": 104,
  "total_qualifying": 71,
  "buys": [
    {
      "symbol": "TSLA",
      "price": 379.88,
      "signal": "BUY",
      "score": 85,
      "pos_pct": 17.6,
      "width_pct": 17.4,
      "vol_ratio": 0.29,
      "stop": 361.23,
      "target": 432.86,
      "entry_low": 368.6,
      "entry_high": 384.67,
      "note": "price at the floor of a clean range"
    },
    {
      "symbol": "AVGO",
      "price": 367.97,
      "signal": "BUY",
      "score": 80,
      "pos_pct": 19.8,
      "width_pct": 16.3,
      "vol_ratio": 0.34,
      "stop": 349.3,
      "target": 414.64,
      "entry_low": 356.43,
      "entry_high": 370.98,
      "note": "price at the floor of a clean range"
    },
    {
      "symbol": "PGR",
      "price": 209.82,
      "signal": "BUY",
      "score": 77,
      "pos_pct": 21.5,
      "width_pct": 18.7,
      "vol_ratio": 0.22,
      "stop": 197.71,
      "target": 239.38,
      "entry_low": 201.74,
      "entry_high": 211.15,
      "note": "price at the floor of a clean range"
    },
    {
      "symbol": "ETN",
      "price": 396.52,
      "signal": "BUY",
      "score": 76,
      "pos_pct": 17.3,
      "width_pct": 12.5,
      "vol_ratio": 0.32,
      "stop": 380.34,
      "target": 436.74,
      "entry_low": 388.1,
      "entry_high": 400.26,
      "note": "price at the floor of a clean range"
    },
    {
      "symbol": "SLB",
      "price": 46.47,
      "signal": "BUY",
      "score": 76,
      "pos_pct": 22.0,
      "width_pct": 19.2,
      "vol_ratio": 0.23,
      "stop": 43.7,
      "target": 53.14,
      "entry_low": 44.59,
      "entry_high": 46.73,
      "note": "price at the floor of a clean range"
    }
  ],
  "watches": [],
  "all_setups": [
    {
      "symbol": "TSLA",
      "price": 379.88,
      "signal": "BUY",
      "score": 85,
      "pos_pct": 17.6,
      "width_pct": 17.4,
      "vol_ratio": 0.29,
      "stop": 361.23,
      "target": 432.86,
      "entry_low": 368.6,
      "entry_high": 384.67,
      "note": "price at the floor of a clean range"
    },
    {
      "symbol": "AVGO",
      "price": 367.97,
      "signal": "BUY",
      "score": 80,
      "pos_pct": 19.8,
      "width_pct": 16.3,
      "vol_ratio": 0.34,
      "stop": 349.3,
      "target": 414.64,
      "entry_low": 356.43,
      "entry_high": 370.98,
      "note": "price at the floor of a clean range"
    },
    {
      "symbol": "PGR",
      "price": 209.82,
      "signal": "BUY",
      "score": 77,
      "pos_pct": 21.5,
      "width_pct": 18.7,
      "vol_ratio": 0.22,
      "stop": 197.71,
      "target": 239.38,
      "entry_low": 201.74,
      "entry_high": 211.15,
      "note": "price at the floor of a clean range"
    },
    {
      "symbol": "ETN",
      "price": 396.52,
      "signal": "BUY",
      "score": 76,
      "pos_pct": 17.3,
      "width_pct": 12.5,
      "vol_ratio": 0.32,
      "stop": 380.34,
      "target": 436.74,
      "entry_low": 388.1,
      "entry_high": 400.26,
      "note": "price at the floor of a clean range"
    },
    {
      "symbol": "SLB",
      "price": 46.47,
      "signal": "BUY",
      "score": 76,
      "pos_pct": 22.0,
      "width_pct": 19.2,
      "vol_ratio": 0.23,
      "stop": 43.7,
      "target": 53.14,
      "entry_low": 44.59,
      "entry_high": 46.73,
      "note": "price at the floor of a clean range"
    },
    {
      "symbol": "NFLX",
      "price": 68.21,
      "signal": "WAIT",
      "score": 93,
      "pos_pct": 0.0,
      "width_pct": 10.7,
      "vol_ratio": 1.34,
      "stop": 69.44,
      "target": 78.45,
      "entry_low": null,
      "entry_high": null,
      "note": "mid-range, no edge yet"
    },
    {
      "symbol": "ZTS",
      "price": 77.04,
      "signal": "WAIT",
      "score": 93,
      "pos_pct": 65.1,
      "width_pct": 12.0,
      "vol_ratio": 0.15,
      "stop": 70.04,
      "target": 80.02,
      "entry_low": null,
      "entry_high": null,
      "note": "mid-range, no edge yet"
    },
    {
      "symbol": "MCD",
      "price": 273.62,
      "signal": "WAIT",
      "score": 92,
      "pos_pct": 41.1,
      "width_pct": 8.8,
      "vol_ratio": 0.21,
      "stop": 258.81,
      "target": 287.29,
      "entry_low": null,
      "entry_high": null,
      "note": "mid-range, no edge yet"
    },
    {
      "symbol": "HD",
      "price": 347.84,
      "signal": "WAIT",
      "score": 91,
      "pos_pct": 70.4,
      "width_pct": 11.5,
      "vol_ratio": 0.23,
      "stop": 315.27,
      "target": 358.85,
      "entry_low": null,
      "entry_high": null,
      "note": "mid-range, no edge yet"
    },
    {
      "symbol": "MS",
      "price": 216.37,
      "signal": "WAIT",
      "score": 91,
      "pos_pct": 37.8,
      "width_pct": 12.4,
      "vol_ratio": 0.5,
      "stop": 202.59,
      "target": 232.25,
      "entry_low": null,
      "entry_high": null,
      "note": "mid-range, no edge yet"
    },
    {
      "symbol": "PH",
      "price": 968.37,
      "signal": "WAIT",
      "score": 89,
      "pos_pct": 52.4,
      "width_pct": 8.0,
      "vol_ratio": 0.22,
      "stop": 910.75,
      "target": 1003.79,
      "entry_low": null,
      "entry_high": null,
      "note": "mid-range, no edge yet"
    },
    {
      "symbol": "DE",
      "price": 602.42,
      "signal": "WAIT",
      "score": 87,
      "pos_pct": 41.5,
      "width_pct": 10.8,
      "vol_ratio": 0.22,
      "stop": 564.92,
      "target": 638.99,
      "entry_low": null,
      "entry_high": null,
      "note": "mid-range, no edge yet"
    },
    {
      "symbol": "DUK",
      "price": 127.21,
      "signal": "WAIT",
      "score": 86,
      "pos_pct": 58.0,
      "width_pct": 6.1,
      "vol_ratio": 0.25,
      "stop": 120.37,
      "target": 130.37,
      "entry_low": null,
      "entry_high": null,
      "note": "mid-range, no edge yet"
    },
    {
      "symbol": "GS",
      "price": 1075.34,
      "signal": "WAIT",
      "score": 86,
      "pos_pct": 47.9,
      "width_pct": 15.1,
      "vol_ratio": 0.33,
      "stop": 982.94,
      "target": 1153.99,
      "entry_low": null,
      "entry_high": null,
      "note": "mid-range, no edge yet"
    },
    {
      "symbol": "PEP",
      "price": 139.26,
      "signal": "WAIT",
      "score": 86,
      "pos_pct": 32.0,
      "width_pct": 10.7,
      "vol_ratio": 0.28,
      "stop": 131.96,
      "target": 149.04,
      "entry_low": null,
      "entry_high": null,
      "note": "mid-range, no edge yet"
    },
    {
      "symbol": "BRK-B",
      "price": 497.56,
      "signal": "WAIT",
      "score": 85,
      "pos_pct": 44.0,
      "width_pct": 5.5,
      "vol_ratio": 0.47,
      "stop": 476.05,
      "target": 512.58,
      "entry_low": null,
      "entry_high": null,
      "note": "mid-range, no edge yet"
    },
    {
      "symbol": "LIN",
      "price": 522.35,
      "signal": "WAIT",
      "score": 85,
      "pos_pct": 37.6,
      "width_pct": 8.2,
      "vol_ratio": 0.27,
      "stop": 496.64,
      "target": 548.2,
      "entry_low": null,
      "entry_high": null,
      "note": "mid-range, no edge yet"
    },
    {
      "symbol": "NVDA",
      "price": 202.81,
      "signal": "WAIT",
      "score": 84,
      "pos_pct": 53.8,
      "width_pct": 12.7,
      "vol_ratio": 0.46,
      "stop": 186.0,
      "target": 213.99,
      "entry_low": null,
      "entry_high": null,
      "note": "mid-range, no edge yet"
    },
    {
      "symbol": "SO",
      "price": 97.01,
      "signal": "WAIT",
      "score": 84,
      "pos_pct": 67.6,
      "width_pct": 7.5,
      "vol_ratio": 0.28,
      "stop": 90.46,
      "target": 99.26,
      "entry_low": null,
      "entry_high": null,
      "note": "mid-range, no edge yet"
    },
    {
      "symbol": "FDX",
      "price": 317.27,
      "signal": "WAIT",
      "score": 83,
      "pos_pct": 40.2,
      "width_pct": 10.8,
      "vol_ratio": 0.17,
      "stop": 297.98,
      "target": 336.92,
      "entry_low": null,
      "entry_high": null,
      "note": "mid-range, no edge yet"
    },
    {
      "symbol": "GOOGL",
      "price": 345.76,
      "signal": "WAIT",
      "score": 83,
      "pos_pct": 34.5,
      "width_pct": 13.6,
      "vol_ratio": 0.3,
      "stop": 323.6,
      "target": 375.27,
      "entry_low": null,
      "entry_high": null,
      "note": "mid-range, no edge yet"
    },
    {
      "symbol": "COST",
      "price": 947.98,
      "signal": "WAIT",
      "score": 81,
      "pos_pct": 53.3,
      "width_pct": 8.4,
      "vol_ratio": 0.24,
      "stop": 889.07,
      "target": 983.71,
      "entry_low": null,
      "entry_high": null,
      "note": "mid-range, no edge yet"
    },
    {
      "symbol": "BKNG",
      "price": 180.28,
      "signal": "WAIT",
      "score": 80,
      "pos_pct": 66.8,
      "width_pct": 14.7,
      "vol_ratio": 0.21,
      "stop": 160.85,
      "target": 188.31,
      "entry_low": null,
      "entry_high": null,
      "note": "mid-range, no edge yet"
    },
    {
      "symbol": "GE",
      "price": 354.75,
      "signal": "WAIT",
      "score": 80,
      "pos_pct": 39.6,
      "width_pct": 13.7,
      "vol_ratio": 0.41,
      "stop": 329.8,
      "target": 382.49,
      "entry_low": null,
      "entry_high": null,
      "note": "mid-range, no edge yet"
    },
    {
      "symbol": "LOW",
      "price": 214.9,
      "signal": "WAIT",
      "score": 78,
      "pos_pct": 36.9,
      "width_pct": 10.7,
      "vol_ratio": 0.25,
      "stop": 202.62,
      "target": 228.81,
      "entry_low": null,
      "entry_high": null,
      "note": "mid-range, no edge yet"
    },
    {
      "symbol": "SYK",
      "price": 323.34,
      "signal": "WAIT",
      "score": 78,
      "pos_pct": 66.1,
      "width_pct": 12.7,
      "vol_ratio": 0.32,
      "stop": 292.43,
      "target": 336.15,
      "entry_low": null,
      "entry_high": null,
      "note": "mid-range, no edge yet"
    },
    {
      "symbol": "NKE",
      "price": 44.21,
      "signal": "WAIT",
      "score": 76,
      "pos_pct": 72.0,
      "width_pct": 14.6,
      "vol_ratio": 0.18,
      "stop": 39.2,
      "target": 45.85,
      "entry_low": null,
      "entry_high": null,
      "note": "mid-range, no edge yet"
    },
    {
      "symbol": "CSCO",
      "price": 111.62,
      "signal": "WAIT",
      "score": 74,
      "pos_pct": 27.4,
      "width_pct": 13.9,
      "vol_ratio": 0.23,
      "stop": 105.38,
      "target": 122.43,
      "entry_low": null,
      "entry_high": null,
      "note": "mid-range, no edge yet"
    },
    {
      "symbol": "WMT",
      "price": 116.07,
      "signal": "WAIT",
      "score": 74,
      "pos_pct": 64.1,
      "width_pct": 12.8,
      "vol_ratio": 0.33,
      "stop": 105.11,
      "target": 121.01,
      "entry_low": null,
      "entry_high": null,
      "note": "mid-range, no edge yet"
    },
    {
      "symbol": "CI",
      "price": 288.51,
      "signal": "WAIT",
      "score": 73,
      "pos_pct": 46.7,
      "width_pct": 11.6,
      "vol_ratio": 0.48,
      "stop": 268.19,
      "target": 305.44,
      "entry_low": null,
      "entry_high": null,
      "note": "mid-range, no edge yet"
    },
    {
      "symbol": "UNH",
      "price": 428.2,
      "signal": "WAIT",
      "score": 73,
      "pos_pct": 47.0,
      "width_pct": 15.8,
      "vol_ratio": 0.42,
      "stop": 390.62,
      "target": 461.62,
      "entry_low": null,
      "entry_high": null,
      "note": "mid-range, no edge yet"
    },
    {
      "symbol": "VRTX",
      "price": 490.96,
      "signal": "WAIT",
      "score": 73,
      "pos_pct": 50.4,
      "width_pct": 19.2,
      "vol_ratio": 0.14,
      "stop": 438.59,
      "target": 533.67,
      "entry_low": null,
      "entry_high": null,
      "note": "mid-range, no edge yet"
    },
    {
      "symbol": "KO",
      "price": 83.06,
      "signal": "WAIT",
      "score": 72,
      "pos_pct": 62.2,
      "width_pct": 8.8,
      "vol_ratio": 0.42,
      "stop": 77.17,
      "target": 85.68,
      "entry_low": null,
      "entry_high": null,
      "note": "mid-range, no edge yet"
    },
    {
      "symbol": "LLY",
      "price": 1180.06,
      "signal": "WAIT",
      "score": 71,
      "pos_pct": 59.2,
      "width_pct": 15.8,
      "vol_ratio": 0.27,
      "stop": 1057.64,
      "target": 1249.45,
      "entry_low": null,
      "entry_high": null,
      "note": "mid-range, no edge yet"
    },
    {
      "symbol": "CB",
      "price": 354.27,
      "signal": "WAIT",
      "score": 70,
      "pos_pct": 74.6,
      "width_pct": 13.4,
      "vol_ratio": 0.33,
      "stop": 315.56,
      "target": 365.29,
      "entry_low": null,
      "entry_high": null,
      "note": "mid-range, no edge yet"
    },
    {
      "symbol": "TJX",
      "price": 155.28,
      "signal": "WAIT",
      "score": 68,
      "pos_pct": 36.9,
      "width_pct": 12.8,
      "vol_ratio": 0.24,
      "stop": 145.3,
      "target": 167.29,
      "entry_low": null,
      "entry_high": null,
      "note": "mid-range, no edge yet"
    },
    {
      "symbol": "AMD",
      "price": 484.01,
      "signal": "WAIT",
      "score": 64,
      "pos_pct": 0.0,
      "width_pct": 18.9,
      "vol_ratio": 0.44,
      "stop": 481.96,
      "target": 584.73,
      "entry_low": null,
      "entry_high": null,
      "note": "mid-range, no edge yet"
    },
    {
      "symbol": "EMR",
      "price": 141.44,
      "signal": "WAIT",
      "score": 63,
      "pos_pct": 40.8,
      "width_pct": 14.5,
      "vol_ratio": 0.34,
      "stop": 130.88,
      "target": 152.88,
      "entry_low": null,
      "entry_high": null,
      "note": "mid-range, no edge yet"
    },
    {
      "symbol": "ISRG",
      "price": 353.05,
      "signal": "WAIT",
      "score": 63,
      "pos_pct": 0.0,
      "width_pct": 17.3,
      "vol_ratio": 1.64,
      "stop": 370.93,
      "target": 443.84,
      "entry_low": null,
      "entry_high": null,
      "note": "mid-range, no edge yet"
    },
    {
      "symbol": "C",
      "price": 130.55,
      "signal": "WAIT",
      "score": 62,
      "pos_pct": 0.0,
      "width_pct": 12.8,
      "vol_ratio": 0.29,
      "stop": 128.59,
      "target": 147.96,
      "entry_low": null,
      "entry_high": null,
      "note": "mid-range, no edge yet"
    },
    {
      "symbol": "CME",
      "price": 245.82,
      "signal": "WAIT",
      "score": 62,
      "pos_pct": 69.3,
      "width_pct": 18.2,
      "vol_ratio": 0.14,
      "stop": 213.94,
      "target": 258.0,
      "entry_low": null,
      "entry_high": null,
      "note": "mid-range, no edge yet"
    },
    {
      "symbol": "HON",
      "price": 228.62,
      "signal": "WAIT",
      "score": 62,
      "pos_pct": 31.0,
      "width_pct": 15.5,
      "vol_ratio": 0.11,
      "stop": 213.74,
      "target": 252.0,
      "entry_low": null,
      "entry_high": null,
      "note": "mid-range, no edge yet"
    },
    {
      "symbol": "HCA",
      "price": 380.34,
      "signal": "WAIT",
      "score": 60,
      "pos_pct": 34.9,
      "width_pct": 21.3,
      "vol_ratio": 0.2,
      "stop": 346.91,
      "target": 429.54,
      "entry_low": null,
      "entry_high": null,
      "note": "mid-range, no edge yet"
    },
    {
      "symbol": "ELV",
      "price": 368.96,
      "signal": "WAIT",
      "score": 59,
      "pos_pct": 0.0,
      "width_pct": 17.9,
      "vol_ratio": 0.23,
      "stop": 362.6,
      "target": 436.24,
      "entry_low": null,
      "entry_high": null,
      "note": "mid-range, no edge yet"
    },
    {
      "symbol": "RTX",
      "price": 197.25,
      "signal": "WAIT",
      "score": 58,
      "pos_pct": 70.9,
      "width_pct": 12.7,
      "vol_ratio": 0.24,
      "stop": 177.35,
      "target": 203.94,
      "entry_low": null,
      "entry_high": null,
      "note": "mid-range, no edge yet"
    },
    {
      "symbol": "BLK",
      "price": 1073.73,
      "signal": "WAIT",
      "score": 55,
      "pos_pct": 71.2,
      "width_pct": 18.8,
      "vol_ratio": 0.21,
      "stop": 928.27,
      "target": 1125.0,
      "entry_low": null,
      "entry_high": null,
      "note": "mid-range, no edge yet"
    },
    {
      "symbol": "MDLZ",
      "price": 62.15,
      "signal": "EXIT",
      "score": 92,
      "pos_pct": 93.1,
      "width_pct": 8.1,
      "vol_ratio": 0.26,
      "stop": 56.62,
      "target": 62.48,
      "entry_low": null,
      "entry_high": null,
      "note": "at/above the ceiling \u2014 take profits, no new longs"
    },
    {
      "symbol": "PG",
      "price": 152.31,
      "signal": "EXIT",
      "score": 88,
      "pos_pct": 87.3,
      "width_pct": 6.5,
      "vol_ratio": 0.35,
      "stop": 141.29,
      "target": 153.49,
      "entry_low": null,
      "entry_high": null,
      "note": "at/above the ceiling \u2014 take profits, no new longs"
    },
    {
      "symbol": "MO",
      "price": 74.55,
      "signal": "EXIT",
      "score": 87,
      "pos_pct": 100.0,
      "width_pct": 8.9,
      "vol_ratio": 0.41,
      "stop": 66.71,
      "target": 74.15,
      "entry_low": null,
      "entry_high": null,
      "note": "at/above the ceiling \u2014 take profits, no new longs"
    },
    {
      "symbol": "CL",
      "price": 94.31,
      "signal": "EXIT",
      "score": 80,
      "pos_pct": 76.9,
      "width_pct": 8.3,
      "vol_ratio": 0.21,
      "stop": 86.89,
      "target": 96.01,
      "entry_low": null,
      "entry_high": null,
      "note": "at/above the ceiling \u2014 take profits, no new longs"
    }
  ]
}